composer/__init__.py
composer/constructs.py
composer/schedule.py
couple-0.1.0.dist-info/WHEEL
couple-0.1.0.dist-info/METADATA
couple-0.1.0.dist-info/RECORD
