Metadata-Version: 2.1
Name: couple
Version: 0.1.0
Summary: For orchestration using AWS Step Functions
License: MIT
Keywords: orchestration,aws,cloud
Author-email: Stephan Fitzpatrick <knowsuchagency@gmail.com>
Requires-Python: >=3.8
Classifier: License :: OSI Approved :: MIT License
Classifier: Programming Language :: Python :: 3
Classifier: Programming Language :: Python :: 3.8
Classifier: Programming Language :: Python :: 3.9
Requires-Dist: aws-cdk.aws_events
Requires-Dist: aws-cdk.aws_events_targets
Requires-Dist: aws-cdk.aws_lambda_python
Requires-Dist: aws-cdk.aws_stepfunctions_tasks
Requires-Dist: aws-cdk.core
Project-URL: Repository, https://github.com/knowsuchagency/composer
Project-URL: homepage, https://github.com/knowsuchagency/composer
